mail_satvadev/.DS_Store
mail_satvadev/__init__.py
mail_satvadev/apps.py
mail_satvadev/filters.py
mail_satvadev/messages.py
mail_satvadev/tasks.py
mail_satvadev-1.0.10.dist-info/METADATA
mail_satvadev-1.0.10.dist-info/WHEEL
mail_satvadev-1.0.10.dist-info/RECORD
