Metadata-Version: 2.4
Name: mail_satvadev
Version: 1.0.10
Summary: Template for email
Author: satva.dev
Author-email: info@satva.dev
Requires-Python: >=3.14,<4.0
Classifier: License :: OSI Approved :: MIT License
Classifier: Operating System :: OS Independent
Classifier: Programming Language :: Python :: 3
Classifier: Programming Language :: Python :: 3.14
Requires-Dist: celery (>=5.2.3,<6.0.0)
Requires-Dist: django (>=5.2.8)
Requires-Dist: django-celery-beat (>=2.2.1,<3.0.0)
Requires-Dist: django-celery-results (>=2.2.0,<3.0.0)
Requires-Dist: psycopg2-binary (>=2.9.9,<3.0.0)
Project-URL: Homepage, https://gitlab.com/satvaspace/_tools/python/mail_satvadev
